nuimages/__init__.py
nuimages/nuimages.py
nuimages/export/export_release.py
nuimages/scripts/render_images.py
nuimages/scripts/render_rare_classes.py
nuimages/tests/__init__.py
nuimages/tests/assert_download.py
nuimages/tests/test_attributes.py
nuimages/tests/test_foreign_keys.py
nuimages/utils/__init__.py
nuimages/utils/test_nuimages.py
nuimages/utils/utils.py
nuscenes/__init__.py
nuscenes/nuscenes.py
nuscenes/can_bus/can_bus_api.py
nuscenes/eval/__init__.py
nuscenes/eval/common/__init__.py
nuscenes/eval/common/config.py
nuscenes/eval/common/data_classes.py
nuscenes/eval/common/loaders.py
nuscenes/eval/common/render.py
nuscenes/eval/common/utils.py
nuscenes/eval/detection/__init__.py
nuscenes/eval/detection/algo.py
nuscenes/eval/detection/config.py
nuscenes/eval/detection/constants.py
nuscenes/eval/detection/data_classes.py
nuscenes/eval/detection/evaluate.py
nuscenes/eval/detection/render.py
nuscenes/eval/detection/utils.py
nuscenes/eval/detection/configs/detection_cvpr_2019.json
nuscenes/eval/detection/tests/__init__.py
nuscenes/eval/detection/tests/test_algo.py
nuscenes/eval/detection/tests/test_data_classes.py
nuscenes/eval/detection/tests/test_evaluate.py
nuscenes/eval/detection/tests/test_loader.py
nuscenes/eval/detection/tests/test_utils.py
nuscenes/eval/lidarseg/__init__.py
nuscenes/eval/lidarseg/evaluate.py
nuscenes/eval/lidarseg/render.py
nuscenes/eval/lidarseg/utils.py
nuscenes/eval/lidarseg/validate_submission.py
nuscenes/eval/lidarseg/tests/__init__.py
nuscenes/eval/panoptic/__init__.py
nuscenes/eval/panoptic/baselines.py
nuscenes/eval/panoptic/evaluate.py
nuscenes/eval/panoptic/get_panoptic_from_seg_det_or_track.py
nuscenes/eval/panoptic/panoptic_seg_evaluator.py
nuscenes/eval/panoptic/panoptic_track_evaluator.py
nuscenes/eval/panoptic/utils.py
nuscenes/eval/prediction/__init__.py
nuscenes/eval/prediction/baseline_model_inference.py
nuscenes/eval/prediction/compute_metrics.py
nuscenes/eval/prediction/config.py
nuscenes/eval/prediction/data_classes.py
nuscenes_devkit-1.1.10.dist-info/LICENSE.txt
nuscenes_devkit-1.1.10.dist-info/METADATA
nuscenes_devkit-1.1.10.dist-info/WHEEL
nuscenes_devkit-1.1.10.dist-info/top_level.txt
nuscenes_devkit-1.1.10.dist-info/RECORD
