Metadata-Version: 2.1
Name: nuscenes-devkit
Version: 1.1.10
Summary: The official devkit of the nuScenes dataset (www.nuscenes.org).
Home-page: https://github.com/nutonomy/nuscenes-devkit
Author: Holger Caesar, Oscar Beijbom, Qiang Xu, Varun Bankiti, Alex H. Lang, Sourabh Vora, Venice Erin Liong, Sergi Widjaja, Kiwoo Shin, Caglayan Dicle, Freddy Boulton, Whye Kit Fong, Asha Asvathaman, Lubing Zhou et al.
Author-email: nuscenes@motional.com
License: cc-by-nc-sa-4.0
Platform: UNKNOWN
Classifier: Programming Language :: Python :: 3.6
Classifier: Operating System :: OS Independent
Classifier: License :: Free for non-commercial use
Requires-Python: >=3.6
Requires-Dist: cachetools
Requires-Dist: descartes
Requires-Dist: fire
Requires-Dist: jupyter
Requires-Dist: matplotlib (<=3.5.2)
Requires-Dist: numpy
Requires-Dist: opencv-python
Requires-Dist: Pillow (>6.2.1)
Requires-Dist: pyquaternion (>=0.9.5)
Requires-Dist: scikit-learn
Requires-Dist: scipy
Requires-Dist: Shapely (<=1.8.5)
Requires-Dist: tqdm
Requires-Dist: pycocotools (>=2.0.1)
